[
    {
      "lot": "lot 50",
      "name": "Product1",
      "author": "John Doe",
      "imageUrl": "https://images.pexels.com/photos/1496373/pexels-photo-1496373.jpeg?auto=compress&cs=tinysrgb&w=1260&h=750&dpr=1",
      "altText": "Front of men's Basic Tee in black0.",
      "materials":"Flashe vinyl paint and oil on canvas",
      "size": "95 7/10 × 71 7/10 in | 243 × 182 cm",
      "title": "Basic Tee1",
      "color": "Black",
      "price": "35",
      "link": "#"
    },
    {
      "name": "Product2",
      "imageUrl": "https://images.pexels.com/photos/1402787/pexels-photo-1402787.jpeg",
      "altText": "Front of men's Basic Tee in black1.",
      "title": "Basic Tee2",
      "color": "Black",
      "materials":"Flashe vinyl paint and oil on canvas",
      "size": "95 7/10 × 71 7/10 in | 243 × 182 cm",
      "price": "35",
      "link": "#",
      "lot": "lot 51"
    },
    {
      "name": "Product3",
      "imageUrl": "https://flowbite.com/docs/images/carousel/carousel-1.svg",
      "altText": "Front of men's Basic Tee in black2.",
      "title": "Basic Tee3",
      "color": "Black",
      "price": "$35",
      "link": "#",
      "lot": "lot 52"
    },
    {
      "name": "Product4",
      "lot": "lot 53",
      "imageUrl": "https://flowbite.com/docs/images/carousel/carousel-1.svg",
      "altText": "Front of men's Basic Tee in black3.",
      "title": "Basic Tee4",
      "color": "Black",
      "price": "$35",
      "link": "#"
    },{
      "name": "Product5",
      "lot": "lot 54",
      "imageUrl": "https://flowbite.com/docs/images/carousel/carousel-1.svg",
      "altText": "Front of men's Basic Tee in black4.",
      "title": "Basic Tee5",
      "color": "Black",
      "price": "$35",
      "link": "#"
    },{
      "name": "Product6",
      "lot": "lot 55",
      "imageUrl": "https://flowbite.com/docs/images/carousel/carousel-1.svg",
      "altText": "Front of men's Basic Tee in black5.",
      "title": "Basic Tee6",
      "color": "Black",
      "price": "$35",
      "link": "#"
    },{
      "name": "Product7",
      "lot": "lot 56",
      "imageUrl": "https://flowbite.com/docs/images/carousel/carousel-1.svg",
      "altText": "Front of men's Basic Tee in black6.",
      "title": "Basic Tee7",
      "color": "Black",
      "price": "$35",
      "link": "#"
    },
    {
      "name": "Product8",
      "lot": "lot 57",
      "imageUrl": "https://flowbite.com/docs/images/carousel/carousel-1.svg",
      "altText": "Front of men's Basic Tee in black7.",
      "title": "Basic Tee8",
      "color": "Black",
      "price": "$35",
      "link": "#"
    },{
      "name": "Product9",
      "lot": "lot 58",
      "imageUrl": "https://flowbite.com/docs/images/carousel/carousel-1.svg",
      "altText": "Front of men's Basic Tee in .",
      "title": "Basic Tee9",
      "color": "Black",
      "price": "$35",
      "link": "#"
    },{
      "name": "Product10",
      "lot": "lot 59",
      "imageUrl": "https://flowbite.com/docs/images/carousel/carousel-1.svg",
      "altText": "Front of men's Basic Tee .",
      "title": "Basic Tee10",
      "color": "Black",
      "price": "$35",
      "link": "#"
    },

    {
      "name": "Product11",
      "lot": "lot 60",
      "imageUrl": "https://flowbite.com/docs/images/carousel/carousel-1.svg",
      "altText": "Front of men's Basic .",
      "title": "Basic Tee11",
      "color": "Black",
      "price": "$35",
      "link": "#"
    }
  ]
  